setup.py
django_archive_mixin/__init__.py
django_archive_mixin/managers.py
django_archive_mixin/mixins.py
django_archive_mixin/utils.py
django_archive_mixin.egg-info/PKG-INFO
django_archive_mixin.egg-info/SOURCES.txt
django_archive_mixin.egg-info/dependency_links.txt
django_archive_mixin.egg-info/not-zip-safe
django_archive_mixin.egg-info/top_level.txt