Metadata-Version: 1.1
Name: django-archive-mixin
Version: 0.1.0
Summary: Archive/soft delete Django models.
Home-page: https://github.com/LucasRoesler/django-archive-mixin
Author: Lucas Roesler
Author-email: roesler.lucas@gmail.com
License: MIT
Keywords: django,model,mixin,soft delete,delete
Platform: OS Independent
Classifier: Development Status :: 5 - Production/Stable
Classifier: Framework :: Django
Classifier: Intended Audience :: Developers
Classifier: License :: OSI Approved :: BSD License
Classifier: Operating System :: OS Independent
Classifier: Programming Language :: Python
Classifier: Programming Language :: Python :: 2
Classifier: Programming Language :: Python :: 2.7
Classifier: Programming Language :: Python :: 3
Classifier: Programming Language :: Python :: 3.3
Classifier: Topic :: Internet :: WWW/HTTP
